XPER/.DS_Store
XPER/__init__.py
XPER/compute/EM.py
XPER/compute/Optimisation.py
XPER/compute/Performance.py
XPER/compute/XGBoost_model.py
XPER/compute/__init__.py
XPER/compute/xgboost_model.joblib
XPER/datasets/__init__.py
XPER/datasets/adult.data
XPER/datasets/load_data.py
XPER/datasets/sample.py
XPER/datasets/boston/BostonHousing.csv
XPER/datasets/loan/Loan_Status.csv
XPER/viz/Visualisation.py
XPER/viz/__init__.py
XPER/viz/figures/force_plot.pdf
XPER-0.0.89.dist-info/LICENSE
XPER-0.0.89.dist-info/METADATA
XPER-0.0.89.dist-info/WHEEL
XPER-0.0.89.dist-info/top_level.txt
XPER-0.0.89.dist-info/RECORD
