Metadata-Version: 2.1
Name: XPER
Version: 0.0.89
Summary: XPER (eXplainable PERformance) is a methodology designed 
Home-page: https://github.com/hi-paris/XPER
Author: Sebastien Saurin, Christophe Hurlin, Christophe Perignon,
Author-email: engineer.hi.paris@gmail.com
License: MIT license
Keywords: XPER
Classifier: Development Status :: 2 - Pre-Alpha
Classifier: Intended Audience :: Developers
Classifier: License :: OSI Approved :: MIT License
Classifier: Environment :: Console
Classifier: Operating System :: OS Independent
Classifier: Operating System :: POSIX :: Linux
Classifier: Operating System :: MacOS
Classifier: Operating System :: POSIX
Classifier: Operating System :: Microsoft :: Windows
Classifier: Natural Language :: English
Classifier: Programming Language :: Python :: 3
Classifier: Programming Language :: Python :: 3.8
Classifier: Programming Language :: Python :: 3.9
Classifier: Programming Language :: Python :: 3.10
Requires-Python: >=3.8
License-File: LICENSE
Requires-Dist: numpy
Requires-Dist: pandas
Requires-Dist: scipy
Requires-Dist: scikit-learn
Requires-Dist: shap
Requires-Dist: seaborn
Requires-Dist: matplotlib
Requires-Dist: xgboost
Requires-Dist: statsmodels
Requires-Dist: tqdm
Requires-Dist: plotly
